farquest/__init__.py
farquest/_base_client.py
farquest/_client.py
farquest/_compat.py
farquest/_constants.py
farquest/_exceptions.py
farquest/_files.py
farquest/_models.py
farquest/_qs.py
farquest/_resource.py
farquest/_response.py
farquest/_streaming.py
farquest/_types.py
farquest/_version.py
farquest/py.typed
farquest/_utils/__init__.py
farquest/_utils/_logs.py
farquest/_utils/_proxy.py
farquest/_utils/_streams.py
farquest/_utils/_sync.py
farquest/_utils/_transform.py
farquest/_utils/_typing.py
farquest/_utils/_utils.py
farquest/lib/.keep
farquest/resources/__init__.py
farquest/resources/auth.py
farquest/resources/organizations.py
farquest/resources/quests.py
farquest/resources/session.py
farquest/resources/quest/__init__.py
farquest/resources/quest/completions.py
farquest/resources/quest/quest.py
farquest/resources/quest/types.py
farquest/resources/quest/validation.py
farquest/types/__init__.py
farquest/types/auth_callback_params.py
farquest/types/organization_create_params.py
farquest/types/quest_complete_params.py
farquest/types/quest_create_params.py
farquest/types/session_create_correlated_params.py
farquest/types/quest/__init__.py
farquest-0.0.1a0.dist-info/METADATA
farquest-0.0.1a0.dist-info/WHEEL
farquest-0.0.1a0.dist-info/licenses/LICENSE
farquest-0.0.1a0.dist-info/RECORD
